swenv/__init__.py
swenv/__main__.py
swenv/_version.py
swenv/apt.py
swenv/ca.py
swenv/configure.py
swenv/detect.py
swenv/docker.py
swenv/env.py
swenv/git.py
swenv/npm.py
swenv/pip.py
swenv/proxy.py
swenv/settings.py
swenv/status.py
swenv/update.py
swenv/utils.py
swenv/bin/swenv
swenv/bin/swenv.ps1
swenv-1.0.2.dist-info/licenses/LICENSE.txt
swenv-1.0.2.dist-info/METADATA
swenv-1.0.2.dist-info/WHEEL
swenv-1.0.2.dist-info/entry_points.txt
swenv-1.0.2.dist-info/top_level.txt
swenv-1.0.2.dist-info/RECORD
