Metadata-Version: 2.4
Name: swenv
Version: 1.0.2
Summary: Switch system and application settings based on the detected network environment.
Author-email: Sébastien Hocquet <seb@ipamo.net>
Project-URL: Homepage, https://gitlab.com/ipamo/swenv
Project-URL: Bug Tracker, https://gitlab.com/ipamo/swenv
Keywords: environment,env,linux,workstation,station,switch
Classifier: Operating System :: OS Independent
Classifier: Programming Language :: Python :: 3
Requires-Python: >=3.9.2
License-File: LICENSE.txt
Dynamic: license-file
